odoo/addons/stock_picking_availability_filter/README.rst
odoo/addons/stock_picking_availability_filter/__init__.py
odoo/addons/stock_picking_availability_filter/__manifest__.py
odoo/addons/stock_picking_availability_filter/i18n/it.po
odoo/addons/stock_picking_availability_filter/i18n/stock_picking_availability_filter.pot
odoo/addons/stock_picking_availability_filter/models/__init__.py
odoo/addons/stock_picking_availability_filter/models/stock_picking.py
odoo/addons/stock_picking_availability_filter/readme/CONTRIBUTORS.rst
odoo/addons/stock_picking_availability_filter/readme/DESCRIPTION.rst
odoo/addons/stock_picking_availability_filter/static/description/icon.png
odoo/addons/stock_picking_availability_filter/static/description/index.html
odoo/addons/stock_picking_availability_filter/tests/__init__.py
odoo/addons/stock_picking_availability_filter/tests/test_stock_picking_availability_filter.py
odoo/addons/stock_picking_availability_filter/views/stock_picking_views.xml
odoo_addon_stock_picking_availability_filter-16.0.1.0.0.2.dist-info/METADATA
odoo_addon_stock_picking_availability_filter-16.0.1.0.0.2.dist-info/WHEEL
odoo_addon_stock_picking_availability_filter-16.0.1.0.0.2.dist-info/top_level.txt
odoo_addon_stock_picking_availability_filter-16.0.1.0.0.2.dist-info/RECORD
